{
    "intervention1" :{
    "client": "Rémi",
    "technicien": "Aurélien",
    "date": "2021-10-08",
    "lieu" : "Lille",
    "panne": "lave-linge",
    "piece": "tambour",
    "tmpEcoule": "2h30",
    "etatPanne": "correct",
    "satisfaction": "content",
    "duree": "4h00"
},
    "intervention2" : {
    "client": "Aurélien",
    "technicien": "Aya",
    "date": "2021-09-17",
    "lieu" : "Paris",
    "panne": "voiture",
    "piece": "moteur",
    "tmpEcoule": "1h30",
    "etatPanne": "mauvaise",
    "satisfaction": "heureux",
    "duree": "5h00"
},
    "intervention3" : {
    "client": "Florimond",
    "technicien": "Rémi",
    "date": "2021-07-25",
    "lieu" : "Marseille",
    "panne": "moto",
    "piece": "guidon",
    "tmpEcoule": "1h00",
    "etatPanne": "bonne",
    "satisfaction": "content",
    "duree": "2h00"
},
    "intervention4" : {
    "client": "Nicolas",
    "technicien": "tobey",
    "date": "2021-01-14",
    "lieu" : "Lyon",
    "panne": "télé",
    "piece": "écran",
    "tmpEcoule": "30 min",
    "etatPanne": "correct",
    "satisfaction": "content",
    "duree": "1h30"
},
    "intervention5" : {
    "client": "Andrew",
    "technicien": "Tom",
    "date": "2021-08-24",
    "lieu" : "Lille",
    "panne": "tondeuse",
    "piece": "moteur",
    "tmpEcoule": "1h00",
    "etatPanne": "correct",
    "satisfaction": "content",
    "duree": "1h45"
}
}